LineStacker/__init__.py
LineStacker/OneD_Stacker/__init__.py
LineStacker/analysisTools/__init__.py
LineStacker/image/__init__.py
LineStacker/interval/__init__.py
LineStacker/interval/fpu.py
LineStacker/interval/imath.py
LineStacker/line_image/__init__.py
LineStacker/modsub/__init__.py
LineStacker/pb/__init__.py
LineStacker/tools/__init__.py
LineStacker/tools/fit/__init__.py
LineStacker/uv/__init__.py
LineStacker-1.5.3.dist-info/LICENSE
LineStacker-1.5.3.dist-info/METADATA
LineStacker-1.5.3.dist-info/WHEEL
LineStacker-1.5.3.dist-info/top_level.txt
LineStacker-1.5.3.dist-info/RECORD
